{
    "props": {
        "face_rect": [
            177,
            630,
            541,
            541
        ],
        "kp_eye_left_inner": [
            387,
            765
        ],
        "kp_eye_left_outer": [
            288,
            765
        ],
        "kp_eye_right_inner": [
            518,
            760
        ],
        "kp_eye_right_outer": [
            611,
            760
        ],
        "kp_mouth_left": [
            546,
            1013
        ],
        "kp_mouth_right": [
            349,
            1013
        ],
        "kp_nose_tip": [
            447,
            854
        ],
        "kp_under_lip_bottom": [
            447,
            1046
        ],
        "kp_upper_lip_top": [
            452,
            971
        ],
        "features": [
            2.543493,
            4.492305,
            6.355979,
            -5.586407,
            5.169445,
            1.027859,
            -4.890947,
            1.951282,
            0.780281,
            5.595136,
            -8.250689,
            -8.498843,
            -5.066319,
            7.020835,
            5.386013,
            -11.654549,
            -5.4276,
            4.385916,
            4.445891,
            -0.063757,
            -2.417956,
            3.401982,
            -10.417505,
            -6.154669,
            8.092666,
            3.090955,
            -1.608554,
            0.53322,
            6.473588,
            0.995015,
            -0.400429,
            3.648886,
            -1.389772,
            -2.522828,
            -2.338217,
            4.395875,
            3.320519,
            4.763676,
            -1.026283,
            2.874896,
            -2.654873,
            -6.0583,
            -8.922924,
            2.657223,
            4.23888,
            8.172718,
            4.444169,
            4.654301,
            -7.348276,
            -2.737493,
            4.789794,
            -0.882915,
            1.952749,
            0.452579,
            1.779306,
            2.795242,
            -4.240498,
            0.489582,
            -2.42376,
            2.029209
        ]
    },
    "image_size": [
        870,
        1918
    ],
    "process_time_in_milliseconds": 957
}
