{
    "props": {
        "face_rect": [
            103,
            772,
            567,
            567
        ],
        "kp_eye_left_inner": [
            318,
            913
        ],
        "kp_eye_left_outer": [
            226,
            928
        ],
        "kp_eye_right_inner": [
            451,
            902
        ],
        "kp_eye_right_outer": [
            558,
            908
        ],
        "kp_mouth_left": [
            502,
            1143
        ],
        "kp_mouth_right": [
            303,
            1158
        ],
        "kp_nose_tip": [
            364,
            1025
        ],
        "kp_under_lip_bottom": [
            400,
            1189
        ],
        "kp_upper_lip_top": [
            390,
            1132
        ],
        "features": [
            4.624859,
            6.733034,
            -1.582137,
            3.925225,
            1.33385,
            6.561588,
            1.917929,
            1.225245,
            4.625495,
            -8.156549,
            -1.190587,
            -3.400695,
            1.962867,
            -3.11475,
            8.185025,
            -4.814163,
            -0.369614,
            -1.568214,
            1.478474,
            1.61132,
            4.067827,
            3.445156,
            -1.555517,
            6.446693,
            -4.113349,
            1.866852,
            -6.257821,
            -1.692044,
            6.830805,
            -7.936742,
            0.71294,
            -4.810975,
            -1.665393,
            4.017819,
            -0.89447,
            0.269968,
            1.374497,
            1.996033,
            0.223014,
            -1.539337,
            -1.675116,
            -2.999079,
            6.651217,
            -0.463205,
            4.840031,
            -7.608359,
            -4.72128,
            -0.425318,
            5.655678,
            0.250012,
            -1.307867,
            6.060843,
            -1.520309,
            1.690325,
            0.308845,
            -3.638094,
            -3.156729,
            4.590423,
            -2.22785,
            4.776501
        ]
    },
    "image_size": [
        870,
        1918
    ],
    "process_time_in_milliseconds": 763
}
