{
  "props": {
    "face_rect": [
      280,
      495,
      387,
      387
    ],
    "kp_eye_left_inner": [
      427,
      592
    ],
    "kp_eye_left_outer": [
      349,
      589
    ],
    "kp_eye_right_inner": [
      512,
      599
    ],
    "kp_eye_right_outer": [
      561,
      602
    ],
    "kp_mouth_left": [
      531,
      761
    ],
    "kp_mouth_right": [
      427,
      765
    ],
    "kp_nose_tip": [
      508,
      660
    ],
    "kp_under_lip_bottom": [
      489,
      784
    ],
    "kp_upper_lip_top": [
      495,
      739
    ],
    "features": [
      2.872918,
      6.257246,
      -0.838072,
      -1.268207,
      4.084299,
      -2.779964,
      0.097715,
      2.783322,
      5.303671,
      -8.534541,
      2.63279,
      -4.722816,
      7.679698,
      -3.34616,
      3.816415,
      -3.040283,
      -2.367031,
      6.393615,
      -6.28335,
      3.02119,
      5.70873,
      -5.822849,
      7.152285,
      2.591165,
      -1.551805,
      0.125863,
      -9.357496,
      -0.12399,
      -2.837021,
      -2.75616,
      -0.63479,
      -0.27089,
      -3.013157,
      1.595477,
      -3.340827,
      3.289501,
      2.712023,
      -2.92746,
      -0.255471,
      -2.895653,
      -0.175585,
      -0.762614,
      1.184794,
      0.1828,
      7.469019,
      -1.964192,
      -2.776515,
      1.255702,
      3.350463,
      -0.414921,
      2.979561,
      12.601572,
      3.080865,
      2.116735,
      0.636067,
      -3.579342,
      -3.658709,
      0.768365,
      -2.023705,
      3.000592
    ]
  },
  "image_size": [
    720,
    1280
  ],
  "process_time_in_milliseconds": 1398,
  "ground_truth": {
    "yaw": 25.0,
    "pitch": 5.0,
    "roll": 3.0
  }
}
