{
    "props": {
        "face_rect": [
            185,
            640,
            545,
            545
        ],
        "kp_eye_left_inner": [
            398,
            777
        ],
        "kp_eye_left_outer": [
            293,
            777
        ],
        "kp_eye_right_inner": [
            526,
            772
        ],
        "kp_eye_right_outer": [
            626,
            768
        ],
        "kp_mouth_left": [
            558,
            1023
        ],
        "kp_mouth_right": [
            357,
            1028
        ],
        "kp_nose_tip": [
            457,
            868
        ],
        "kp_under_lip_bottom": [
            457,
            1055
        ],
        "kp_upper_lip_top": [
            462,
            982
        ],
        "features": [
            2.710658,
            4.378121,
            6.618373,
            -6.179056,
            4.92079,
            1.527413,
            -5.083002,
            2.000838,
            -0.244647,
            6.174304,
            -8.306297,
            -8.852453,
            -4.476884,
            7.123025,
            5.207218,
            -11.533904,
            -5.660527,
            4.772103,
            4.298249,
            0.126451,
            -2.392802,
            3.225152,
            -10.326037,
            -7.641661,
            7.192523,
            2.910716,
            -1.6356,
            0.341667,
            6.717355,
            1.222323,
            0.068647,
            3.294848,
            -1.778683,
            -3.006137,
            -2.438416,
            3.352859,
            3.220839,
            4.698003,
            -0.977586,
            3.641895,
            -2.757336,
            -6.130992,
            -9.063974,
            2.645558,
            5.006683,
            8.313313,
            4.552236,
            4.37149,
            -7.233473,
            -3.36097,
            5.646267,
            -1.176097,
            1.778148,
            -0.110099,
            1.005584,
            3.112486,
            -4.168568,
            0.412271,
            -2.25871,
            2.148911
        ]
    },
    "image_size": [
        870,
        1918
    ],
    "process_time_in_milliseconds": 743
}
