{
    "props": {
        "face_rect": [
            571,
            1361,
            1031,
            1031
        ],
        "kp_eye_left_inner": [
            971,
            1619
        ],
        "kp_eye_left_outer": [
            794,
            1619
        ],
        "kp_eye_right_inner": [
            1192,
            1610
        ],
        "kp_eye_right_outer": [
            1360,
            1583
        ],
        "kp_mouth_left": [
            1245,
            2052
        ],
        "kp_mouth_right": [
            953,
            2070
        ],
        "kp_nose_tip": [
            1086,
            1849
        ],
        "kp_under_lip_bottom": [
            1103,
            2105
        ],
        "kp_upper_lip_top": [
            1095,
            2043
        ],
        "features": [
            -3.20606,
            3.857217,
            0.858973,
            -1.594528,
            -0.859845,
            2.036756,
            -6.722937,
            7.301452,
            2.035269,
            -4.208728,
            -4.264728,
            5.682507,
            1.37446,
            -3.134189,
            3.338905,
            4.01787,
            -9.004569,
            -4.287844,
            -8.441595,
            -5.337652,
            2.700922,
            0.338844,
            -1.433207,
            6.996586,
            0.216942,
            -4.766021,
            1.747586,
            0.189339,
            2.623324,
            -3.163367,
            -0.544669,
            -6.14642,
            -10.078147,
            4.989279,
            6.471122,
            0.733638,
            -0.301143,
            -4.053632,
            6.684083,
            8.591974,
            -0.150132,
            -8.304449,
            -1.41587,
            -1.397864,
            -3.316451,
            -2.046239,
            1.785096,
            -3.872511,
            -4.403879,
            -1.535012,
            1.86792,
            4.354143,
            -3.89377,
            -0.704005,
            -8.271564,
            1.248529,
            -5.188582,
            3.639028,
            -4.018427,
            1.966233
        ]
    },
    "image_size": [
        2160,
        3840
    ],
    "process_time_in_milliseconds": 2596
}
